cli_test_helpers/__init__.py
cli_test_helpers/commands.py
cli_test_helpers/decorators.py
cli_test_helpers/mixins.py
cli_test_helpers-4.2.0.dist-info/licenses/LICENSE
docs/api.rst
docs/conf.py
docs/contributing.rst
docs/index.rst
docs/installation.rst
docs/other.rst
docs/techniques.rst
docs/tutorial.rst
cli_test_helpers-4.2.0.dist-info/METADATA
cli_test_helpers-4.2.0.dist-info/WHEEL
cli_test_helpers-4.2.0.dist-info/top_level.txt
cli_test_helpers-4.2.0.dist-info/RECORD
