Metadata-Version: 2.4
Name: cli-test-helpers
Version: 4.2.0
Summary: Useful helpers for writing tests for your Python CLI program.
Author-email: Peter Bittner <peter@painless.software>
Maintainer-email: Peter Bittner <peter@painless.software>
License:                     GNU GENERAL PUBLIC LICENSE
Project-URL: homepage, https://github.com/painless-software/python-cli-test-helpers
Project-URL: Documentation, https://python-cli-test-helpers.readthedocs.io/
Keywords: python,cli,testing,helpers
Classifier: Development Status :: 5 - Production/Stable
Classifier: Intended Audience :: Developers
Classifier: License :: OSI Approved :: GNU General Public License v3 (GPLv3)
Classifier: Programming Language :: Python
Classifier: Programming Language :: Python :: 3
Classifier: Programming Language :: Python :: 3 :: Only
Classifier: Programming Language :: Python :: 3.8
Classifier: Programming Language :: Python :: 3.9
Classifier: Programming Language :: Python :: 3.10
Classifier: Programming Language :: Python :: 3.11
Classifier: Programming Language :: Python :: 3.12
Classifier: Programming Language :: Python :: 3.13
Classifier: Programming Language :: Python :: 3.14
Classifier: Programming Language :: Python :: Implementation :: CPython
Classifier: Programming Language :: Python :: Implementation :: PyPy
Classifier: Topic :: Software Development :: Testing
Classifier: Topic :: Software Development :: Testing :: Mocking
Classifier: Topic :: Software Development :: Testing :: Unit
Requires-Python: >=3.8
License-File: LICENSE
Dynamic: license-file
